overwatch_ci_helper/__init__.py
overwatch_ci_helper/needs.py
overwatch_ci_helper/template.config.yaml
overwatch_ci_helper-0.1.2.dist-info/METADATA
overwatch_ci_helper-0.1.2.dist-info/WHEEL
overwatch_ci_helper-0.1.2.dist-info/entry_points.txt
overwatch_ci_helper-0.1.2.dist-info/RECORD
